skyline2isocor/__init__.py
skyline2isocor/cli.py
skyline2isocor/test-data/manip_acetate/200324_LLE_TMG_AAdil100.txt
skyline2isocor/test-data/manip_acetate/isotopic_data_isocor.tsv
skyline2isocor/test-data/maud_bug/isocor.tsv
skyline2isocor/test-data/maud_bug/PFPP_13C_POS_SK_results_LLE.csv
skyline2isocor/test-data/output_test.tsv
skyline2isocor/test-data/skyline_output.csv
skyline2isocor/test-data/tmp_amandine/Quantif.tsv
skyline2isocor-1.0.0.dist-info/entry_points.txt
skyline2isocor-1.0.0.dist-info/LICENSE
skyline2isocor-1.0.0.dist-info/METADATA
skyline2isocor-1.0.0.dist-info/WHEEL
skyline2isocor-1.0.0.dist-info/RECORD
