Metadata-Version: 2.1
Name: skyline2isocor
Version: 1.0.0
Summary: Convert skyline output to IsoCor input format
Author: legregam
Author-email: legregam@insa-toulouse.fr
Requires-Python: >=3.9,<4.0
Classifier: Programming Language :: Python :: 3
Classifier: Programming Language :: Python :: 3.9
Classifier: Programming Language :: Python :: 3.10
Classifier: Programming Language :: Python :: 3.11
Classifier: Programming Language :: Python :: 3.12
Requires-Dist: pandas (>=2.1.4,<3.0.0)
